aureus/__init__.py
aureus/dbconnector/__init__.py
aureus/exceptions/__init__.py
aureus/helper/__init__.py
aureus/route/__init__.py
aureus/session/__init__.py
aureus/template_engine/__init__.py
aureus/view/__init__.py
aureus/wsgi_adapter/__init__.py
aureus-0.0.3.dist-info/METADATA
aureus-0.0.3.dist-info/RECORD
aureus-0.0.3.dist-info/WHEEL
aureus-0.0.3.dist-info/top_level.txt
