Metadata-Version: 2.1
Name: aureus
Version: 0.0.3
Summary: a simple python web framework
Home-page: https://github.com/YouwangDeng/aureus
Author: Youwang Deng
Author-email: dengyouwang@gmail.com
Maintainer: Youwang Deng
Maintainer-email: dengyouwang@gmail.com
License: BSD License
Platform: all
Classifier: Development Status :: 3 - Alpha
Classifier: Operating System :: OS Independent
Classifier: Intended Audience :: Developers
Classifier: License :: OSI Approved :: BSD License
Classifier: Programming Language :: Python
Classifier: Programming Language :: Python :: Implementation
Classifier: Programming Language :: Python :: 2
Classifier: Programming Language :: Python :: 2.7
Classifier: Programming Language :: Python :: 3
Classifier: Programming Language :: Python :: 3.4
Classifier: Programming Language :: Python :: 3.5
Classifier: Programming Language :: Python :: 3.6
Classifier: Topic :: Software Development :: Libraries
Requires-Dist: Werkzeug (>=0.14.1)
Requires-Dist: PyMySQL (>=0.9.2)
